mysql/__init__.py
rbk-0.0.1.dist-info/LICENSE
rbk-0.0.1.dist-info/METADATA
rbk-0.0.1.dist-info/WHEEL
rbk-0.0.1.dist-info/top_level.txt
rbk-0.0.1.dist-info/RECORD
